scanit_cli/__init__.py
scanit_cli/scanit.py
scanit_cli-1.0.5.dist-info/LICENSE
scanit_cli-1.0.5.dist-info/METADATA
scanit_cli-1.0.5.dist-info/WHEEL
scanit_cli-1.0.5.dist-info/entry_points.txt
scanit_cli-1.0.5.dist-info/top_level.txt
scanit_cli-1.0.5.dist-info/RECORD
