Metadata-Version: 2.1
Name: scanit-cli
Version: 1.0.5
Summary: Scan files for virus online using VirusTotal directly from your cli.
Home-page: https://github.com/shivamsn97/ScanIt/tree/module
Author: Shivam Saini
Author-email: shivamsn97@gmail.com
License: MIT
Platform: UNKNOWN
Classifier: Programming Language :: Python :: 3
Classifier: License :: OSI Approved :: MIT License
Classifier: Operating System :: OS Independent
Requires-Python: >=3.0
Requires-Dist: vt-py
Requires-Dist: colorama
